roblox_py/__init__.py
roblox_python-0.1.3.dist-info/METADATA
roblox_python-0.1.3.dist-info/WHEEL
roblox_python-0.1.3.dist-info/top_level.txt
roblox_python-0.1.3.dist-info/RECORD
