Metadata-Version: 2.1
Name: roblox-python
Version: 0.1.3
Summary: Library Python Roblox
Author: TV_Kirill
Author-email: kirill.shishkov2007@gmail.com
